Srini_CRMA/Folders.py
Srini_CRMA/Limits.py
Srini_CRMA/Recipe.py
Srini_CRMA/__init__.py
Srini_CRMA/assign_sf_login.py
Srini_CRMA/dashboard.py
Srini_CRMA/data_connectors.py
Srini_CRMA/dataflow.py
Srini_CRMA/dataflow_analysis.py
Srini_CRMA/dataset_fields.py
Srini_CRMA/dataset_metadata.py
Srini_CRMA/field_analysis.py
Srini_CRMA/object_fields.py
Srini_CRMA/recipe_analysis.py
Srini_CRMA/upload_all_crma_metadata.py
Srini_CRMA/upload_to_crma.py
Srini_CRMA-0.4.1.9.3.dist-info/LICENSE.txt
Srini_CRMA-0.4.1.9.3.dist-info/METADATA
Srini_CRMA-0.4.1.9.3.dist-info/WHEEL
Srini_CRMA-0.4.1.9.3.dist-info/top_level.txt
Srini_CRMA-0.4.1.9.3.dist-info/RECORD
