Metadata-Version: 2.1
Name: Srini_CRMA
Version: 0.4.1.9.3
Summary: Extract CRMA Metadata
Author: Srinivasan Ravindran
Author-email: r.srinivasan3@gmail.com
Classifier: Programming Language :: Python :: 3
Classifier: License :: OSI Approved :: MIT License
Classifier: Operating System :: OS Independent
License-File: LICENSE.txt
